Workbook

Sheet Assumptions_Summary
A1: Big Star Land Acquisition – Assumptions Summary (PPM Aligned)
A2: Total Capital Raised | B2: =Assumptions!B4
A3: Land Acquisition
A4: Average Purchase Price per Parcel | B4: =Assumptions!B12
A5: Total Parcels | B5: =Assumptions!B11
A7: Exit Pricing
A8: Conservative Exit Price per MW | B8: =Assumptions!B14
A9: Base Case Exit Price per MW | B9: =Assumptions!B23
A11: Costs
A12: Power Study Cost per Parcel | B12: =Assumptions!B15
A13: Closing Costs (%) | B13: =Assumptions!B17
A15: EPC + Equipment Upside
A16: Revenue per MW | B16: =Assumptions!B31

Sheet Assumptions
A1: Big Star Land Acquisition – Model Inputs
A3: FUND-LEVEL INPUTS
A4: Total Capital Raised | B4: 7500000
A5: Number of Parcels | B5: 4
A6: Investor Share of Net Proceeds | B6: 0.25
A7: Cash Return Cap | B7: 1.2
A8: Conversion Price per Share | B8: 1.5
A9: Shares Outstanding (fully diluted) | B9: 21000000
A11: CONSERVATIVE CASE INPUTS
A12: Purchase Price per Parcel | B12: 1000000
A13: MW Capacity per Parcel | B13: 40
A14: Exit Price per MW | B14: 200000
A15: Power Study Cost per Parcel | B15: 50000
A16: Legal / Diligence per Parcel | B16: 50000
A17: Closing Cost % of Purchase | B17: 0.05
A20: BASE CASE INPUTS
A21: Purchase Price per Parcel | B21: 1000000
A22: MW Capacity per Parcel | B22: 50
A23: Exit Price per MW | B23: 350000
A24: Power Study Cost per Parcel | B24: 50000
A25: Legal / Diligence per Parcel | B25: 50000
A26: Closing Cost % of Purchase | B26: 0.05
A29: VALUATION INPUTS (ILLUSTRATIVE)
A30: Big Star Economic Stake (Land Only) | B30: 0.51
A31: EPC + Equipment Revenue per MW | B31: 275000
A32: EPC Attach Rate – Low | B32: 0.25
A33: EPC Attach Rate – Base | B33: 0.5
A34: EPC Attach Rate – High | B34: 0.75
A35: Net Margin on Land Proceeds (illustrative) | B35: 0.25
A36: Net Margin on EPC Revenue (illustrative) | B36: 0.25
A37: P/E Multiple – Low | B37: 8
A38: P/E Multiple – Base | B38: 10
A39: P/E Multiple – High | B39: 12

Sheet Land_Economics
A1: Scenario | B1: Purchase Price | C1: Power Study | D1: Legal/Diligence | E1: Closing Costs | F1: Total Cost | G1: MW | H1: Exit $/MW | I1: Gross Exit Value | J1: Net Proceeds
A2: Conservative | B2: =Assumptions!$B$12 | C2: =Assumptions!$B$15 | D2: =Assumptions!$B$16 | E2: =Assumptions!$B$12*Assumptions!$B$17 | F2: =SUM(B2:E2) | G2: =Assumptions!$B$13 | H2: =Assumptions!$B$14 | I2: =G2*H2 | J2: =I2-F2
A3: Base | B3: =Assumptions!$B$21 | C3: =Assumptions!$B$24 | D3: =Assumptions!$B$25 | E3: =Assumptions!$B$21*Assumptions!$B$26 | F3: =SUM(B3:E3) | G3: =Assumptions!$B$22 | H3: =Assumptions!$B$23 | I3: =G3*H3 | J3: =I3-F3

Sheet Portfolio_Summary
A1: Scenario | B1: Net Proceeds / Parcel | C1: Parcels | D1: Total Net Proceeds | E1: Investor Share (25%) | F1: Cash Required (120%) | G1: Coverage Ratio
A2: Conservative | B2: =Land_Economics!$J$2 | C2: =Assumptions!$B$5 | D2: =B2*C2 | E2: =D2*Assumptions!$B$6 | F2: =Assumptions!$B$4*Assumptions!$B$7 | G2: =E2/F2
A3: Base | B3: =Land_Economics!$J$3 | C3: =Assumptions!$B$5 | D3: =B3*C3 | E3: =D3*Assumptions!$B$6 | F3: =Assumptions!$B$4*Assumptions!$B$7 | G3: =E3/F3

Sheet Waterfall
A1: Month | B1: Investor Distribution (Base) | C1: Cumulative Returned
A2: 0 | B2: 0 | C2: =SUM($B$2:B2)
A3: 1 | B3: 0 | C3: =SUM($B$2:B3)
A4: 2 | B4: 0 | C4: =SUM($B$2:B4)
A5: 3 | B5: =MIN((Assumptions!$B$4*Assumptions!$B$7)-IFERROR(C4,0), Land_Economics!$J$3*Assumptions!$B$6) | C5: =SUM($B$2:B5)
A6: 4 | B6: =MIN((Assumptions!$B$4*Assumptions!$B$7)-IFERROR(C5,0), Land_Economics!$J$3*Assumptions!$B$6) | C6: =SUM($B$2:B6)
A7: 5 | B7: =MIN((Assumptions!$B$4*Assumptions!$B$7)-IFERROR(C6,0), Land_Economics!$J$3*Assumptions!$B$6) | C7: =SUM($B$2:B7)
A8: 6 | B8: =MIN((Assumptions!$B$4*Assumptions!$B$7)-IFERROR(C7,0), Land_Economics!$J$3*Assumptions!$B$6) | C8: =SUM($B$2:B8)

Sheet Equity_Conversion
A1: Investment | B1: Cash Returned (120%) | C1: Shares Issued (@$1.50)
A2: 100000 | B2: =A2*Assumptions!$B$7 | C2: =A2/Assumptions!$B$8
A3: 250000 | B3: =A3*Assumptions!$B$7 | C3: =A3/Assumptions!$B$8
A4: 500000 | B4: =A4*Assumptions!$B$7 | C4: =A4/Assumptions!$B$8
A5: 1000000 | B5: =A5*Assumptions!$B$7 | C5: =A5/Assumptions!$B$8

Sheet EPC_Upside
A1: Scenario | B1: MW / Parcel | C1: Parcels | D1: EPC $ / MW | E1: Attach Rate | F1: EPC Revenue (Attach-Adjusted) | G1: EPC Revenue (100% Attach)
A2: Conservative | B2: =Assumptions!$B$13 | C2: =Assumptions!$B$5 | D2: =Assumptions!$B$31 | E2: =Assumptions!$B$32 | F2: =B2*C2*D2*E2 | G2: =B2*C2*D2
A3: Base | B3: =Assumptions!$B$22 | C3: =Assumptions!$B$5 | D3: =Assumptions!$B$31 | E3: =Assumptions!$B$33 | F3: =B3*C3*D3*E3 | G3: =B3*C3*D3

Sheet Valuation_Sensitivity
A1: Illustrative Valuation Sensitivity (Non-Binding)
A2: Scenario | B2: Total MW (Portfolio) | C2: Total Net Proceeds (Land) | D2: Investor Distributions Paid | E2: Big Star Share of Land Proceeds (51%) | F2: Big Star EPC + Equipment Rev (100%) | G2: Illustrative Earnings (Land + EPC) | H2: Implied Share Price
A3: Conservative | B3: =Assumptions!$B$5*Assumptions!$B$13 | C3: =Portfolio_Summary!$D$2 | D3: =MIN(C3*Assumptions!$B$6, Assumptions!$B$4*Assumptions!$B$7) | E3: =(C3-D3)*Assumptions!$B$30 | F3: =B3*Assumptions!$B$31*Assumptions!$B$32 | G3: =E3*Assumptions!$B$35 + F3*Assumptions!$B$36 | H3: =(G3*Assumptions!$B$38)/Assumptions!$B$9
A4: Base | B4: =Assumptions!$B$5*Assumptions!$B$22 | C4: =Portfolio_Summary!$D$3 | D4: =MIN(C4*Assumptions!$B$6, Assumptions!$B$4*Assumptions!$B$7) | E4: =(C4-D4)*Assumptions!$B$30 | F4: =B4*Assumptions!$B$31*Assumptions!$B$33 | G4: =E4*Assumptions!$B$35 + F4*Assumptions!$B$36 | H4: =(G4*Assumptions!$B$38)/Assumptions!$B$9
A6: Attach Rate & P/E Sensitivity (Base Case – Illustrative)
A7: Scenario | B7: Attach Rate | C7: P/E | D7: Implied Share Price (Base)
A8: Low | B8: =Assumptions!$B$32 | C8: =Assumptions!$B$37 | D8: =((( (Portfolio_Summary!$D$3 - MIN(Portfolio_Summary!$D$3*Assumptions!$B$6, Assumptions!$B$4*Assumptions!$B$7) )*Assumptions!$B$30 )*Assumptions!$B$35) + ((Assumptions!$B$5*Assumptions!$B$22)*Assumptions!$B$31*Assumptions!$B$32*Assumptions!$B$36)) * (C8) / Assumptions!$B$9
A9: Base | B9: =Assumptions!$B$33 | C9: =Assumptions!$B$38 | D9: =((( (Portfolio_Summary!$D$3 - MIN(Portfolio_Summary!$D$3*Assumptions!$B$6, Assumptions!$B$4*Assumptions!$B$7) )*Assumptions!$B$30 )*Assumptions!$B$35) + ((Assumptions!$B$5*Assumptions!$B$22)*Assumptions!$B$31*Assumptions!$B$33*Assumptions!$B$36)) * (C9) / Assumptions!$B$9
A10: High | B10: =Assumptions!$B$34 | C10: =Assumptions!$B$39 | D10: =((( (Portfolio_Summary!$D$3 - MIN(Portfolio_Summary!$D$3*Assumptions!$B$6, Assumptions!$B$4*Assumptions!$B$7) )*Assumptions!$B$30 )*Assumptions!$B$35) + ((Assumptions!$B$5*Assumptions!$B$22)*Assumptions!$B$31*Assumptions!$B$34*Assumptions!$B$36)) * (C10) / Assumptions!$B$9
A12: Notes
A13: • Illustrative only. Not a forecast, projection, or promise of performance.
A14: • Investor distributions modeled as 25% of net proceeds capped at 120% of invested capital.
A15: • Big Star economic stake applies to LAND sponsor economics only; EPC + equipment revenue is 100% Big Star.
A16: • Margins, attach rates, and P/E multiples are user-editable in the Assumptions tab.

Sheet Forward_Looking
A1: Forward-Looking Statement
A3: Certain statements in this model and accompanying materials constitute “forward-looking statements” within the meaning of applicable securities laws. Forward-looking statements include, without limitation, statements regarding anticipated transactions, timing of acquisitions and dispositions, expected megawatt capacity, proceeds, EPC and equipment revenue, and illustrative valuation outcomes. These statements are based on current expectations and assumptions and are subject to risks and uncertainties that could cause actual results to differ materially, including market conditions, buyer demand, permitting and interconnection timelines, utility/co-op approvals, diligence outcomes, execution risk, and general economic factors. This model is provided for discussion purposes only and does not constitute an offer to sell or a solicitation of an offer to buy any security. Any offering will be made only by means of definitive offering documents, which will contain additional information and risk factors. No representation or warranty is made as to the accuracy or completeness of the information herein, and the information is subject to change without notice.
